{
    "CTR": [
        {
            "Q": "What type of chart is this?",
            "A": "This chart is a {chord} chart."
        }
    ],
    "VEC": [
        {
            "Q": "How many chords are in this chord chart?",
            "A": "There are {3} chords."
        },
        {
            "Q": "How many outer arcs are in this chord chart?",
            "A": "There are {3} outer arcs."
        }
    ],
    "SRP": [
        {
            "Q": "In the chord chart, what is the next arc in the clockwise direction from arc Health Sciences?",
            "A": "The next arc clockwise from arc Health Sciences is arc {Engineering}."
        },
        {
            "Q": "In the chord chart, what is the next arc in the counterclockwise direction from arc Health Sciences?",
            "A": "The next arc counterclockwise from arc Health Sciences is arc {Business}."
        }
    ],
    "VPR": [
        {
            "Q": "Which arc has the largest output flow in this chord chart?",
            "A": "{Business} has the largest output flow."
        },
        {
            "Q": "Which arc has the largest input flow in this chord chart?",
            "A": "{Health Sciences} has the largest input flow."
        }
    ],
    "VE": [
        {
            "Q": "What is the flow value from Business to Health Sciences in the chord chart?",
            "A": "The flow value is {730}."
        },
        {
            "Q": "What is the flow value from Engineering to Health Sciences in the chord chart?",
            "A": "The flow value is {288}."
        },
        {
            "Q": "What is the flow value from Business to Engineering in the chord chart?",
            "A": "The flow value is {567}."
        }
    ],
    "EVJ": [
        {
            "Q": "What is the maximum flow value between Engineering and Health Sciences in the chord chart?",
            "A": "The maximum flow value between Engineering and Health Sciences is {288}."
        },
        {
            "Q": "What is the minimum flow value between Business and Health Sciences in the chord chart?",
            "A": "The minimum flow value between Business and Health Sciences is {572}."
        },
        {
            "Q": "What is the maximum flow value in the chord chart?",
            "A": "The maximum flow value is {730}."
        },
        {
            "Q": "What is the minimum flow value in the chord chart?",
            "A": "The minimum flow value is {100}."
        }
    ],
    "SC": [
        {
            "Q": "What is the total flow output from Engineering?",
            "A": "The total flow output from Engineering is {604}."
        },
        {
            "Q": "What is the total flow input by Engineering?",
            "A": "The total flow input by Engineering is {667}."
        }
    ],
    "NF": [
        {
            "Q": "Which pairs of nodes in the chord chart have a flow greater than 441? Please list the source node, target node, and the corresponding flow value.",
            "A": "There is a flow of {572} from {Health Sciences} to {Business}, a flow of {730} from {Business} to {Health Sciences}, a flow of {567} from {Business} to {Engineering}."
        },
        {
            "Q": "Which pairs of nodes in the chord chart have a flow less than 441? Please list the source node, target node, and the corresponding flow value.",
            "A": "There is a flow of {100} from {Health Sciences} to {Engineering}, a flow of {288} from {Engineering} to {Health Sciences}, a flow of {316} from {Engineering} to {Business}."
        },
        {
            "Q": "Which pairs of nodes in the chord chart have a flow between 194 and 569? Please list the source node, target node, and the corresponding flow value.",
            "A": "There is a flow of {288} from {Engineering} to {Health Sciences}, a flow of {567} from {Business} to {Engineering}, a flow of {316} from {Engineering} to {Business}."
        }
    ],
    "NC": [
        {
            "Q": "Which flow is larger: from Business to Health Sciences or from Health Sciences to Engineering?",
            "A": "The flow from {Business} to {Health Sciences} is larger."
        },
        {
            "Q": "Which flow is the largest: from Health Sciences to Engineering, from Business to Engineering, or from Health Sciences to Business?",
            "A": "The flow from {Health Sciences} to {Business} is the largest."
        }
    ],
    "MSR": [
        {
            "Q": "Which category has the highest proportion of outgoing flow relative to its total flow?",
            "A": "The category with the highest proportion of outgoing flow relative to its total flow is {Business}."
        },
        {
            "Q": "Which pair has the strongest chord connection in this chord chart?",
            "A": "The strongest chord connection is between {Business} and {Health Sciences}."
        }
    ],
    "VA": [
        {
            "Q": "To minimize the crossings between chords, please reorder the outer arcs and list the reorder arc order in clockwise direction.",
            "A": "The reordered arc order in clockwise direction is: {Arc Engineering, Arc Business, Arc Health Sciences}."
        }
    ]
}