{
    "CTR": [
        {
            "Q": "What type of chart is this?",
            "A": "This chart is a {stacked bar chart}."
        }
    ],
    "VEC": [
        {
            "Q": "How many bars are in this stacked bar chart?",
            "A": "There are {5} bars."
        },
        {
            "Q": "How many stacked segments are in bar Yorkton of this stacked bar chart?",
            "A": "There are {5} stacked bars."
        }
    ],
    "SRP": [
        {
            "Q": "Is this stacked bar chart a horizontal stacked bar chart or a vertical stacked bar chart?",
            "A": "The stacked bar chart is a {vertical} stacked bar chart."
        },
        {
            "Q": "Which category does the leftmost bar represent?",
            "A": "The leftmost bar represents {Brookfield}"
        },
        {
            "Q": "Which category does the rightmost bar represent?",
            "A": "The leftmost bar represents {Zephyr}."
        },
        {
            "Q": "What is the spatial relationship of bar Yorkton relative to the bar Zephyr in terms of horizontal (left/right) direction?",
            "A": "Bar Yorkton is to the {left} of the bar Zephyr."
        },
        {
            "Q": "In the stacked bar of Quarryville, What is the spatial relationship of segment AI relative to the segment Quantum in terms of vertical (above/below) direction?",
            "A": "AI segment is positioned {below} the Quantum segment."
        }
    ],
    "VPR": [
        {
            "Q": "Which City has the highest bar in this stacked bar chart?",
            "A": "The City with the highest bar is {Quarryville}."
        },
        {
            "Q": "Which City has the lowest bar in this stacked bar chart?",
            "A": "The City with the lowest bar is {Zephyr}."
        },
        {
            "Q": "In the stacked bar representing Ironwood, which segment has the highest value?",
            "A": "The segment with the highest value is {Aerospace}."
        },
        {
            "Q": "In the stacked bar representing Brookfield, which segment has the lowest value?",
            "A": "The segment with the lowest value is {AI}."
        }
    ],
    "VE": [
        {
            "Q": "What is the value of the AI segment within the Yorkton bar in the stacked bar chart?",
            "A": "The value of the AI segment is {56.98} billion USD."
        },
        {
            "Q": "What is the value of the AI segment within the Quarryville bar in the stacked bar chart?",
            "A": "The value of the AI segment is {10.00} billion USD."
        },
        {
            "Q": "What is the value of the Aerospace segment within the Zephyr bar in the stacked bar chart?",
            "A": "The value of the Aerospace segment is {14.57} billion USD."
        }
    ],
    "EVJ": [
        {
            "Q": "What is the maximum billion USD among the stacked segments of bar Ironwood?",
            "A": "The maximum billion USD among the stacked segments of bar Ironwood is {88.43} billion USD."
        },
        {
            "Q": "What is the minimum billion USD among the stacked segments of bar Ironwood?",
            "A": "The minimum billion USD among the stacked segments of bar Ironwood is {10.0} billion USD."
        },
        {
            "Q": "In the stacked bar chart, what is the maximum billion USD of the segment Robotics among the bars?",
            "A": "The maximum billion USD among the bars of segment Robotics is {66.38} billion USD."
        },
        {
            "Q": "In the stacked bar chart, what is the minimum billion USD of the segment AI among the bars?",
            "A": "The minimum billion USD among the bars of segment AI is {10.0} billion USD."
        }
    ],
    "SC": [
        {
            "Q": "What is the total value of the bar Yorkton?",
            "A": "The total value of bar Yorkton is {148.71} billion USD."
        },
        {
            "Q": "What is the total value of the bar Zephyr?",
            "A": "The total value of bar Zephyr is {129.31} billion USD."
        },
        {
            "Q": "What is the total value of all columns?",
            "A": "The total value of columns is {782.53} billion USD."
        },
        {
            "Q": "What is the difference between total value of bar Yorkton and Brookfield?",
            "A": "The difference between between total value of bar Yorkton and Brookfield is {7.109999999999985} billion USD."
        }
    ],
    "NF": [
        {
            "Q": "Which bars have total billion USD values exceed 153.73 billion USD? Please list the bar and corresponding values.",
            "A": "{Ironwood} has {158.76} billion USD, {Quarryville} has {204.15} billion USD"
        },
        {
            "Q": "Which bars have total billion USD values below 145.15 billion USD? Please list the bar and corresponding values.",
            "A": "{Zephyr} has {129.31} billion USD, {Brookfield} has {141.6} billion USD"
        },
        {
            "Q": "For bar Yorkton in the stacked bar chart, which segment have billion USD value between 10.0 and 56.709999999999994? Please list the segment and corresponding values.",
            "A": "{Robotics} has {15.29} billion USD, {Quantum} has {56.44} billion USD."
        }
    ],
    "NC": [
        {
            "Q": "Which is larger, the total billion USD of Quarryville or Yorkton?",
            "A": "The total billion USD of the {Quarryville} is larger."
        },
        {
            "Q": "Which is larger, the total billion USD of Ironwood, Zephyr or Quarryville?",
            "A": "The total billion USD of the {Quarryville} is larger."
        },
        {
            "Q": "In the bar Brookfield, which has a larger billion USD value: Aerospace or Computing?",
            "A": "{Computing} has the larger billion USD value."
        },
        {
            "Q": "In the bar Ironwood, which has a larger billion USD value: Aerospace, Computing or Quantum?",
            "A": "{Aerospace} has the larger billion USD value."
        }
    ],
    "MSR": [
        {
            "Q": "Ranking bar by the value of segment Quantum in descending order, which are the top three countries(if the number of bars is less 3,list the existing bars in descending order)?",
            "A": "The top three bar ranked by the value of segment Quantum are: {Yorkton}, {Quarryville}, {Brookfield}."
        }
    ],
    "VA": []
}